python_markdown_nofollow/__init__.py
python_markdown_nofollow/nofollow.py
python_markdown_nofollow-0.0.1.dist-info/METADATA
python_markdown_nofollow-0.0.1.dist-info/WHEEL
python_markdown_nofollow-0.0.1.dist-info/top_level.txt
python_markdown_nofollow-0.0.1.dist-info/RECORD
